KBDD/EGtest.py
KBDD/KGML_to_Matrix.py
KBDD/Network_score_with_cor.py
KBDD/__init__.py
KBDD/alpha_estimation.py
KBDD/connect_adj_set.py
KBDD/deviation_calculation.py
KBDD/generate_ensemble_network.py
KBDD/import_references.py
KBDD/left_adj.py
KBDD/net_gen.py
KBDD/pns_construction.py
KBDD/rightmost_adj.py
KBDD/show_graph_with_labels.py
KBDD/truncated_power_law.py
NEKBDD/KGML_to_Matrix.py
NEKBDD/Network_score_with_cor.py
NEKBDD/__init__.py
NEKBDD/alpha_estimation.py
NEKBDD/deviation_calculation.py
NEKBDD/generate_ensemble_network.py
NEKBDD/import_references.py
NEKBDD/pns_construction.py
NEKBDD/show_graph_with_labels.py
NEKBDD-0.2.0.dist-info/LICENSE.txt
NEKBDD-0.2.0.dist-info/METADATA
NEKBDD-0.2.0.dist-info/WHEEL
NEKBDD-0.2.0.dist-info/top_level.txt
NEKBDD-0.2.0.dist-info/RECORD
