Metadata-Version: 2.1
Name: NEKBDD
Version: 0.2.0
Summary: A package for NEKBDD: a nonparametric ensemble knowledge-based data-driven genetic network construction
Author: Chen-Po Liao
Author-email: liaochenpo@gmail.com
License: MIT
Classifier: License :: OSI Approved :: MIT License
Classifier: Programming Language :: Python :: 3
Requires-Python: >=3.6
License-File: LICENSE.txt
Requires-Dist: numpy
Requires-Dist: pandas
Requires-Dist: powerlaw
